Design.sv
module BCD_to_7Segment (BCD,a,b,c,d,e,f,g,error);
  input [3:0] BCD;    
  output reg a, b, c, d, e, f, g;
  output reg error=1'b0; 

  always @(BCD)
      begin
        case (BCD)
            4'b0000: {a, b, c, d, e, f, g} = 7'b1111110;  
            4'b0001: {a, b, c, d, e, f, g} = 7'b0110000;  
            4'b0010: {a, b, c, d, e, f, g} = 7'b1101101;  
            4'b0011: {a, b, c, d, e, f, g} = 7'b1111001;  
            4'b0100: {a, b, c, d, e, f, g} = 7'b0110011;  
            4'b0101: {a, b, c, d, e, f, g} = 7'b1011011;  
            4'b0110: {a, b, c, d, e, f, g} = 7'b1011111;  
            4'b0111: {a, b, c, d, e, f, g} = 7'b1110000;  
            4'b1000: {a, b, c, d, e, f, g} = 7'b1111111;  
            4'b1001: {a, b, c, d, e, f, g} = 7'b1111011;  
            default:
        begin
                {a, b, c, d, e, f, g} = 7'b0000000;
                error = 1;
        end
        endcase
    end
endmodule

Testbench.sv
module testbench;
  reg [3:0]BCD;
  wire a, b, c, d, e, f, g, error;
  BCD_to_7Segment utt(.BCD(BCD),.a(a),.b(b),.c(c),.d(d),.e(e),.f(f),.g(g),.error(error));
  initial
    begin
      $monitor($time,"BCD[3]=%b,BCD[2]=%b,BCD[1]=%b,BCD[0]=%b,a=%b,b=%b,c=%b,d=%b,e=%b,f=%b,g=%b err=%b",BCD[3],BCD[2],BCD[1],BCD[0],a,b,c,d,e,f,g,error);
      
      	BCD = 4'b0000; #10;  
        BCD = 4'b0001; #10;  
        BCD = 4'b0010; #10;  
        BCD = 4'b0011; #10;  
        BCD = 4'b0100; #10;  
        BCD = 4'b0101; #10;  
        BCD = 4'b0110; #10;  
        BCD = 4'b0111; #10; 
        BCD = 4'b1000; #10;  
        BCD = 4'b1001; #10;  
        BCD = 4'b1010; #10; 
        BCD = 4'b1011; #10; 
        BCD = 4'b1100; #10; 
        BCD = 4'b1101; #10; 
        BCD = 4'b1110; #10; 
        BCD = 4'b1111; #10; 
      #10 $finish;
    end

  initial
    begin
      $dumpfile("dump.vcd");
      $dumpvars(0,testbench);
	  #300
      $finish;
    end
endmodule

dump.vcd
$date
	Mon Nov  4 19:59:43 2024
$end
$version
	Icarus Verilog
$end
$timescale
	1s
$end
$scope module testbench $end
$var wire 1 ! g $end
$var wire 1 " f $end
$var wire 1 # error $end
$var wire 1 $ e $end
$var wire 1 % d $end
$var wire 1 & c $end
$var wire 1 ' b $end
$var wire 1 ( a $end
$var reg 4 ) BCD [3:0] $end
$scope module utt $end
$var wire 4 * BCD [3:0] $end
$var reg 1 ( a $end
$var reg 1 ' b $end
$var reg 1 & c $end
$var reg 1 % d $end
$var reg 1 $ e $end
$var reg 1 # error $end
$var reg 1 " f $end
$var reg 1 ! g $end
$upscope $end
$upscope $end
$enddefinitions $end
$comment Show the parameter values. $end
$dumpall
$end
#0
$dumpvars
b0 *
b0 )
1(
1'
1&
1%
1$
0#
1"
0!
$end
#10
0(
0%
0$
0"
b1 )
b1 *
#20
1(
0&
1%
1$
1!
b10 )
b10 *
#30
1&
0$
b11 )
b11 *
#40
0(
0%
1"
b100 )
b100 *
#50
1(
0'
1%
b101 )
b101 *
#60
1$
b110 )
b110 *
#70
1'
0%
0$
0"
0!
b111 )
b111 *
#80
1%
1$
1"
1!
b1000 )
b1000 *
#90
0$
b1001 )
b1001 *
#100
1#
0(
0'
0&
0%
0"
0!
b1010 )
b1010 *
#110
b1011 )
b1011 *
#120
b1100 )
b1100 *
#130
b1101 )
b1101 *
#140
b1110 )
b1110 *
#150
b1111 )
b1111 *
